sap_nota_pedido/nota_pedido_transaction.py
sap_nota_pedido/session.py
hnt_sap_nota_pedido_library-0.0.7.dist-info/METADATA
hnt_sap_nota_pedido_library-0.0.7.dist-info/WHEEL
hnt_sap_nota_pedido_library-0.0.7.dist-info/top_level.txt
hnt_sap_nota_pedido_library-0.0.7.dist-info/RECORD
